dynetan/__init__.py
dynetan/contact.py
dynetan/datastorage.py
dynetan/gencor.py
dynetan/network.py
dynetan/proctraj.py
dynetan/toolkit.py
dynetan/version.py
dynetan/viz.py
dynetan/vizmod/__init__.py
dynetan/vizmod/community_RGB_colors.csv
dynetan/vizmod/network_color.tcl
dynetan/vizmod/network_menu.tcl
dynetan/vizmod/network_proc.tcl
dynetan/vizmod/network_rep.tcl
dynetan/vizmod/network_view_2.tcl
dynetan-2.2.2.dist-info/METADATA
dynetan-2.2.2.dist-info/WHEEL
dynetan-2.2.2.dist-info/licenses/LICENSE
dynetan-2.2.2.dist-info/RECORD
