Metadata-Version: 2.4
Name: dynetan
Version: 2.2.2
Summary: A Python implementation for Dynamical Network Analysis.
Project-URL: Homepage, https://gitlab.com/comp-biochem-csu/dynetan
Project-URL: Bug Tracker, https://gitlab.com/comp-biochem-csu/dynetan/-/issues
Project-URL: Documentation, https://dynamical-network-analysis.readthedocs.io
Author-email: "Marcelo C. R. Melo" <melomcr@gmail.com>
License-File: LICENSE
Classifier: License :: OSI Approved :: GNU General Public License v3 (GPLv3)
Classifier: Operating System :: OS Independent
Classifier: Programming Language :: Python :: 3
Requires-Python: >=3.9
Requires-Dist: colorama
Requires-Dist: h5py
Requires-Dist: mdanalysis
Requires-Dist: networkx
Requires-Dist: nglview
Requires-Dist: numba
Requires-Dist: numpy
Requires-Dist: pandas
Requires-Dist: python-louvain
Requires-Dist: tqdm
